odoo10_addon_mail_restrict_follower_selection-10.0.1.0.1-py3.8-nspkg.pth
odoo/addons/mail_restrict_follower_selection/README.rst
odoo/addons/mail_restrict_follower_selection/__init__.py
odoo/addons/mail_restrict_follower_selection/__manifest__.py
odoo/addons/mail_restrict_follower_selection/data/ir_actions.xml
odoo/addons/mail_restrict_follower_selection/data/ir_config_parameter.xml
odoo/addons/mail_restrict_follower_selection/i18n/de.po
odoo/addons/mail_restrict_follower_selection/i18n/es.po
odoo/addons/mail_restrict_follower_selection/i18n/fr.po
odoo/addons/mail_restrict_follower_selection/i18n/hr.po
odoo/addons/mail_restrict_follower_selection/i18n/it.po
odoo/addons/mail_restrict_follower_selection/i18n/mail_restrict_follower_selection.pot
odoo/addons/mail_restrict_follower_selection/i18n/pt.po
odoo/addons/mail_restrict_follower_selection/i18n/sl.po
odoo/addons/mail_restrict_follower_selection/models/__init__.py
odoo/addons/mail_restrict_follower_selection/models/mail_wizard_invite.py
odoo/addons/mail_restrict_follower_selection/static/description/icon.png
odoo/addons/mail_restrict_follower_selection/tests/__init__.py
odoo/addons/mail_restrict_follower_selection/tests/test_mail_restrict_follower_selection.py
odoo10_addon_mail_restrict_follower_selection-10.0.1.0.1.dist-info/METADATA
odoo10_addon_mail_restrict_follower_selection-10.0.1.0.1.dist-info/WHEEL
odoo10_addon_mail_restrict_follower_selection-10.0.1.0.1.dist-info/namespace_packages.txt
odoo10_addon_mail_restrict_follower_selection-10.0.1.0.1.dist-info/top_level.txt
odoo10_addon_mail_restrict_follower_selection-10.0.1.0.1.dist-info/RECORD
