Metadata-Version: 2.1
Name: odoo10-addon-mail-restrict-follower-selection
Version: 10.0.1.0.1
Summary: Define a domain from which followers can be selected
Home-page: https://github.com/OCA/social
Author: Therp BV,Odoo Community Association (OCA)
Author-email: support@odoo-community.org
License: AGPL-3
Platform: UNKNOWN
Classifier: Programming Language :: Python
Classifier: Framework :: Odoo
Classifier: Framework :: Odoo :: 10.0
Classifier: License :: OSI Approved :: GNU Affero General Public License v3
Requires-Python: ~=2.7
Requires-Dist: odoo (<10.1dev,>=10.0)
